ioctx/__init__.py
ioctx/backends.py
ioctx/protocol.py
ioctx-0.1.0.dist-info/LICENSE
ioctx-0.1.0.dist-info/METADATA
ioctx-0.1.0.dist-info/WHEEL
ioctx-0.1.0.dist-info/RECORD
