Metadata-Version: 2.1
Name: ioctx
Version: 0.1.0
Summary: A structured effects system for testable side effects in Python
Home-page: https://github.com/username/ioctx-py
License: MIT
Keywords: io,testing,mocking,effects,side-effects
Author: Your Name
Author-email: your.email@example.com
Requires-Python: >=3.9,<4.0
Classifier: Development Status :: 3 - Alpha
Classifier: Intended Audience :: Developers
Classifier: License :: OSI Approved :: MIT License
Classifier: Programming Language :: Python :: 3
Classifier: Programming Language :: Python :: 3.9
Classifier: Programming Language :: Python :: 3.10
Classifier: Programming Language :: Python :: 3.11
Classifier: Programming Language :: Python :: 3
Classifier: Programming Language :: Python :: 3.10
Classifier: Programming Language :: Python :: 3.11
Classifier: Programming Language :: Python :: 3.8
Classifier: Programming Language :: Python :: 3.9
Classifier: Topic :: Software Development :: Libraries
Classifier: Topic :: Software Development :: Testing
Classifier: Topic :: Software Development :: Testing :: Mocking
Provides-Extra: requests
Requires-Dist: requests (>=2.25.0) ; extra == "requests"
Requires-Dist: typing-extensions (>=4.0.0)
Project-URL: Documentation, https://github.com/username/ioctx-py
Project-URL: Repository, https://github.com/username/ioctx-py
